setup.py
muller_gaussian_binomial_distributions/Binomialdistribution.py
muller_gaussian_binomial_distributions/Gaussiandistribution.py
muller_gaussian_binomial_distributions/Generaldistribution.py
muller_gaussian_binomial_distributions/__init__.py
muller_gaussian_binomial_distributions.egg-info/PKG-INFO
muller_gaussian_binomial_distributions.egg-info/SOURCES.txt
muller_gaussian_binomial_distributions.egg-info/dependency_links.txt
muller_gaussian_binomial_distributions.egg-info/not-zip-safe
muller_gaussian_binomial_distributions.egg-info/top_level.txt