Metadata-Version: 1.0
Name: muller-gaussian-binomial-distributions
Version: 0.1
Summary: Gaussian and Binomial distributions package
Home-page: UNKNOWN
Author: Wuppschlander Müller
Author-email: wuppschlandermuller@gmail.com
License: UNKNOWN
Platform: UNKNOWN
